tciifrba/SOS_pasabajo_simple.py
tciifrba/__init__.py
tciifrba/demo_seg_orden1.py
tciifrba/demo_seg_orden2.py
tciifrba/splane.py
tciifrba/tciifrba.py
tciifrba-2.3.dist-info/LICENSE
tciifrba-2.3.dist-info/METADATA
tciifrba-2.3.dist-info/WHEEL
tciifrba-2.3.dist-info/top_level.txt
tciifrba-2.3.dist-info/RECORD
